odyssey/__init__.py
odyssey/__main__.py
odyssey/plugins.py
odyssey-1.0.2.dist-info/entry_points.txt
odyssey-1.0.2.dist-info/LICENSE
odyssey-1.0.2.dist-info/WHEEL
odyssey-1.0.2.dist-info/METADATA
odyssey-1.0.2.dist-info/RECORD
