Metadata-Version: 2.1
Name: odyssey
Version: 1.0.2
Summary: A Multi-SCM Multi-Repository Workspace Management Framework
Home-page: https://github.com/python-odyssey/odyssey
License: MIT
Author: Justin Sharma
Author-email: justin.elite@gmail.com
Requires-Python: >=3.6,<4.0
Classifier: Development Status :: 3 - Alpha
Classifier: Environment :: Console
Classifier: Intended Audience :: Developers
Classifier: Intended Audience :: Information Technology
Classifier: Intended Audience :: Science/Research
Classifier: Intended Audience :: System Administrators
Classifier: License :: OSI Approved :: MIT License
Classifier: Operating System :: MacOS
Classifier: Operating System :: Microsoft :: Windows
Classifier: Operating System :: POSIX :: Linux
Classifier: Programming Language :: Python :: 3
Classifier: Programming Language :: Python :: 3.6
Classifier: Programming Language :: Python :: 3.7
Classifier: Programming Language :: Python :: 3.8
Classifier: Topic :: Software Development :: Build Tools
Classifier: Topic :: Software Development :: Documentation
Classifier: Topic :: Software Development :: Version Control
Requires-Dist: click (>=7.1.2,<8.0.0)
Requires-Dist: click-log (>=0.3.2,<0.4.0)
Requires-Dist: pluggy (>=0.13.1,<0.14.0)
Project-URL: Documentation, https://python-odyssey.readthedocs.io/en/latest/
Project-URL: Repository, https://github.com/python-odyssey/odyssey
